{
    "currentOrders": [
        {
            "customer": "郑州智成软件科技有限公司1",
            "volume": 100
        },
        {
            "customer": "郑州智成软件科技有限公司2",
            "volume": 90
        },
        {
            "customer": "郑州智成软件科技有限公司3",
            "volume": 80
        },
        {
            "customer": "郑州智成软件科技有限公司4",
            "volume": 70
        },
        {
            "customer": "郑州智成软件科技有限公司5",
            "volume": 60
        },
        {
            "customer": "郑州智成软件科技有限公司6",
            "volume": 50
        },
        {
            "customer": "郑州智成软件科技有限公司7",
            "volume": 40
        },
        {
            "customer": "郑州智成软件科技有限公司8",
            "volume": 30
        },
        {
            "customer": "郑州智成软件科技有限公司9",
            "volume": 20
        },
        {
            "customer": "郑州智成软件科技有限公司10",
            "volume": 10
        },
        {
            "customer": "郑州智成软件科技有限公司11",
            "volume": 9
        },
        {
            "customer": "郑州智成软件科技有限公司12",
            "volume": 8
        }
    ],
    "sellInfo": [
        {
            "ordernum": 1000,
            "sellnum": 10000,
            "sum": 2000
        },
        {
            "ordernum": 100,
            "sellnum": 1000,
            "sum": 200
        },
        {
            "ordernum": 5,
            "sellnum": 20,
            "sum": 2
        }
    ],
    "cityOrder": [
        {
            "city": "重庆",
            "ordernum": 100
        },
        {
            "city": "无锡",
            "ordernum": 90
        },
        {
            "city": "成都",
            "ordernum": 80
        },
        {
            "city": "杭州",
            "ordernum": 70
        },
        {
            "city": "武汉",
            "ordernum": 60
        },
        {
            "city": "深圳",
            "ordernum": 50
        },
        {
            "city": "广州",
            "ordernum": 40
        },
        {
            "city": "上海",
            "ordernum": 30
        },
        {
            "city": "北京",
            "ordernum": 20
        },
        {
            "city": "郑州",
            "ordernum": 10
        }
    ]
}